uliweb_comapps/__init__.py
uliweb_comapps/settings.ini
uliweb_comapps/auth/__init__.py
uliweb_comapps/auth/login/README.md
uliweb_comapps/auth/login/__init__.py
uliweb_comapps/auth/login/config.ini
uliweb_comapps/auth/login/settings.ini
uliweb_comapps/auth/login/views.py
uliweb_comapps/auth/login/static/readme.txt
uliweb_comapps/auth/login/static/login/login.css
uliweb_comapps/auth/login/templates/login.html
uliweb_comapps/auth/login/templates/readme.txt
uliweb_comapps/auth/login/templates/register.html
uliweb_comapps/auth/rbac_admin/README.md
uliweb_comapps/auth/rbac_admin/__init__.py
uliweb_comapps/auth/rbac_admin/settings.ini
uliweb_comapps/auth/rbac_admin/views.py
uliweb_comapps/auth/rbac_admin/static/readme.txt
uliweb_comapps/auth/rbac_admin/templates/rbac_admin_layout.html
uliweb_comapps/auth/rbac_admin/templates/readme.txt
uliweb_comapps/auth/rbac_admin/templates/PermissionView/list.html
uliweb_comapps/auth/rbac_admin/templates/PermissionView/view.html
uliweb_comapps/auth/rbac_admin/templates/RoleView/list.html
uliweb_comapps/auth/rbac_admin/templates/RoleView/view.html
uliweb_comapps/auth/superuser/__init__.py
uliweb_comapps/auth/superuser/commands.py
uliweb_comapps/auth/superuser/conf.py
uliweb_comapps/auth/superuser/info.ini
uliweb_comapps/auth/superuser/static/readme.txt
uliweb_comapps/auth/superuser/templates/readme.txt
uliweb_comapps/auth/user_admin/README.md
uliweb_comapps/auth/user_admin/__init__.py
uliweb_comapps/auth/user_admin/config.ini
uliweb_comapps/auth/user_admin/forms.py
uliweb_comapps/auth/user_admin/settings.ini
uliweb_comapps/auth/user_admin/views.py
uliweb_comapps/auth/user_admin/static/readme.txt
uliweb_comapps/auth/user_admin/templates/readme.txt
uliweb_comapps/auth/user_admin/templates/user_admin_layout.html
uliweb_comapps/auth/user_admin/templates/UserAdmin/list.html
uliweb_comapps/auth/user_admin/templates/UserAdmin/view.html
uliweb_comapps/auth/user_admin/templates/UserView/change_password.html
uliweb_comapps-0.2.0.dist-info/METADATA
uliweb_comapps-0.2.0.dist-info/WHEEL
uliweb_comapps-0.2.0.dist-info/top_level.txt
uliweb_comapps-0.2.0.dist-info/RECORD
