Metadata-Version: 2.1
Name: uliweb-comapps
Version: 0.2.0
Summary: uliweb-comapps
Home-page: https://github.com/zhangchunlin/uliweb-comapps
Author: Chunlin Zhang
Author-email: zhangchunlin@gmail.com
License: BSD
Platform: any
Classifier: Development Status :: 4 - Beta
Classifier: Environment :: Web Environment
Classifier: Intended Audience :: Developers
Classifier: License :: OSI Approved :: BSD License
Classifier: Operating System :: OS Independent
Classifier: Programming Language :: Python
Classifier: Topic :: Software Development :: Libraries :: Python Modules
Requires-Dist: uliweb3
